{"v":"5.10.2","fr":25,"ip":0,"op":60,"w":500,"h":500,"nm":"37 elk","ddd":0,"assets":[],"layers":[{"ddd":0,"ind":1,"ty":3,"nm":"Main Stroke width - Color Ctrl","sr":1,"ks":{"o":{"a":0,"k":0,"ix":11},"r":{"a":0,"k":0,"ix":10},"p":{"a":0,"k":[250,250,0],"ix":2,"l":2},"a":{"a":0,"k":[50,50,0],"ix":1,"l":2},"s":{"a":0,"k":[100,100,100],"ix":6,"l":2}},"ao":0,"ef":[{"ty":5,"nm":"Stroke width","np":3,"mn":"ADBE Slider Control","ix":1,"en":1,"ef":[{"ty":0,"nm":"Slider","mn":"ADBE Slider Control-0001","ix":1,"v":{"a":0,"k":16,"ix":1}}]},{"ty":5,"nm":"Base Color","np":3,"mn":"ADBE Color Control","ix":2,"en":1,"ef":[{"ty":2,"nm":"Color","mn":"ADBE Color Control-0001","ix":1,"v":{"a":0,"k":[0.019607843831,0.164705887437,0.458823531866,1],"ix":1}}]},{"ty":5,"nm":"Highlight","np":3,"mn":"ADBE Color Control","ix":3,"en":1,"ef":[{"ty":2,"nm":"Color","mn":"ADBE Color Control-0001","ix":1,"v":{"a":0,"k":[0.992156863213,0.796078443527,0.313725501299,1],"ix":1}}]},{"ty":5,"nm":"Highlight 2","np":3,"mn":"ADBE Color Control","ix":4,"en":1,"ef":[{"ty":2,"nm":"Color","mn":"ADBE Color Control-0001","ix":1,"v":{"a":0,"k":[1,1,1,1],"ix":1}}]},{"ty":5,"nm":"Highlight 3","np":3,"mn":"ADBE Color Control","ix":5,"en":1,"ef":[{"ty":2,"nm":"Color","mn":"ADBE Color Control-0001","ix":1,"v":{"a":0,"k":[0.992156863213,0.376470595598,0.313725501299,1],"ix":1}}]},{"ty":5,"nm":"Stroke width details","np":3,"mn":"ADBE Slider Control","ix":6,"en":1,"ef":[{"ty":0,"nm":"Slider","mn":"ADBE Slider Control-0001","ix":1,"v":{"a":0,"k":18,"ix":1}}]}],"ip":0,"op":65,"st":0,"bm":0},{"ddd":0,"ind":2,"ty":4,"nm":"head","parent":10,"sr":1,"ks":{"o":{"a":0,"k":100,"ix":11},"r":{"a":0,"k":0,"ix":10},"p":{"a":1,"k":[{"i":{"x":0.667,"y":1},"o":{"x":0.333,"y":0},"t":7,"s":[0,-37.585,0],"to":[0,5,0],"ti":[0,3.333,0]},{"i":{"x":0.667,"y":1},"o":{"x":0.333,"y":0},"t":17,"s":[0,-7.585,0],"to":[0,-3.333,0],"ti":[0,1.667,0]},{"i":{"x":0.667,"y":1},"o":{"x":0.333,"y":0},"t":28,"s":[0,-57.585,0],"to":[0,-1.667,0],"ti":[0,-3.333,0]},{"i":{"x":0.667,"y":1},"o":{"x":0.333,"y":0},"t":39,"s":[0,-17.585,0],"to":[0,3.333,0],"ti":[0,3.333,0]},{"t":50,"s":[0,-37.585,0]}],"ix":2,"l":2},"a":{"a":0,"k":[250,328.404,0],"ix":1,"l":2},"s":{"a":0,"k":[100,100,100],"ix":6,"l":2}},"ao":0,"shapes":[{"ty":"gr","it":[{"ind":0,"ty":"sh","ix":1,"ks":{"a":1,"k":[{"i":{"x":0.667,"y":1},"o":{"x":0.333,"y":0},"t":9,"s":[{"i":[[0,0],[4.646,4.631]],"o":[[-4.646,4.631],[0,0]],"v":[[8.413,-1.736],[-8.413,-1.736]],"c":false}]},{"i":{"x":0.667,"y":1},"o":{"x":0.333,"y":0},"t":19,"s":[{"i":[[0,0],[4.646,4.631]],"o":[[-4.646,4.631],[0,0]],"v":[[8.413,8.264],[-8.413,8.264]],"c":false}]},{"i":{"x":0.667,"y":1},"o":{"x":0.333,"y":0},"t":30,"s":[{"i":[[0,0],[4.646,4.63]],"o":[[-4.646,4.63],[0,0]],"v":[[8.413,-14.736],[-8.413,-14.736]],"c":false}]},{"i":{"x":0.667,"y":1},"o":{"x":0.333,"y":0},"t":41,"s":[{"i":[[0,0],[4.646,4.63]],"o":[[-4.646,4.63],[0,0]],"v":[[8.413,8.264],[-8.413,8.264]],"c":false}]},{"t":52,"s":[{"i":[[0,0],[4.646,4.63]],"o":[[-4.646,4.63],[0,0]],"v":[[8.413,-1.736],[-8.413,-1.736]],"c":false}]}],"ix":2},"nm":"Path 1","mn":"ADBE Vector Shape - Group","hd":false},{"ty":"st","c":{"a":0,"k":[0,0,0,1],"ix":3,"x":"var $bm_rt;\n$bm_rt = thisComp.layer('Main Stroke width - Color Ctrl').effect('Base Color')('Color');"},"o":{"a":0,"k":100,"ix":4},"w":{"a":0,"k":16,"ix":5,"x":"var $bm_rt;\n$bm_rt = thisComp.layer('Main Stroke width - Color Ctrl').effect('Stroke width')('Slider');"},"lc":2,"lj":2,"bm":0,"nm":"Stroke 1","mn":"ADBE Vector Graphic - Stroke","hd":false},{"ty":"tr","p":{"a":0,"k":[250,296.484],"ix":2},"a":{"a":0,"k":[0,0],"ix":1},"s":{"a":0,"k":[100,100],"ix":3},"r":{"a":0,"k":0,"ix":6},"o":{"a":0,"k":100,"ix":7},"sk":{"a":0,"k":0,"ix":4},"sa":{"a":0,"k":0,"ix":5},"nm":"Transform"}],"nm":"Group 1","np":2,"cix":2,"bm":0,"ix":1,"mn":"ADBE Vector Group","hd":false},{"ty":"gr","it":[{"ind":0,"ty":"sh","ix":1,"ks":{"a":1,"k":[{"i":{"x":0.667,"y":1},"o":{"x":0.333,"y":0},"t":9,"s":[{"i":[[0,-9.374],[12.845,0],[0,9.374],[-12.845,0]],"o":[[0,9.374],[-12.845,0],[0,-9.374],[12.845,0]],"v":[[23.258,0],[0,16.973],[-23.258,0],[0,-16.973]],"c":true}]},{"i":{"x":0.667,"y":1},"o":{"x":0.333,"y":0},"t":19,"s":[{"i":[[0,-9.374],[12.845,0],[0,9.374],[-12.845,0]],"o":[[0,9.374],[-12.845,0],[0,-9.374],[12.845,0]],"v":[[23.258,10],[0,26.973],[-23.258,10],[0,-6.973]],"c":true}]},{"i":{"x":0.667,"y":1},"o":{"x":0.333,"y":0},"t":30,"s":[{"i":[[0,-9.374],[12.845,0],[0,9.374],[-12.845,0]],"o":[[0,9.374],[-12.845,0],[0,-9.374],[12.845,0]],"v":[[23.258,-13],[0,3.973],[-23.258,-13],[0,-29.973]],"c":true}]},{"i":{"x":0.667,"y":1},"o":{"x":0.333,"y":0},"t":41,"s":[{"i":[[0,-9.374],[12.845,0],[0,9.374],[-12.845,0]],"o":[[0,9.374],[-12.845,0],[0,-9.374],[12.845,0]],"v":[[23.258,10],[0,26.973],[-23.258,10],[0,-6.973]],"c":true}]},{"t":52,"s":[{"i":[[0,-9.374],[12.845,0],[0,9.374],[-12.845,0]],"o":[[0,9.374],[-12.845,0],[0,-9.374],[12.845,0]],"v":[[23.258,0],[0,16.973],[-23.258,0],[0,-16.973]],"c":true}]}],"ix":2},"nm":"Path 1","mn":"ADBE Vector Shape - Group","hd":false},{"ty":"st","c":{"a":0,"k":[0.20000000298,0.800000011921,0.800000011921,1],"ix":3,"x":"var $bm_rt;\n$bm_rt = thisComp.layer('Main Stroke width - Color Ctrl').effect('Base Color')('Color');"},"o":{"a":0,"k":100,"ix":4},"w":{"a":0,"k":16,"ix":5,"x":"var $bm_rt;\n$bm_rt = thisComp.layer('Main Stroke width - Color Ctrl').effect('Stroke width')('Slider');"},"lc":2,"lj":2,"bm":0,"nm":"Stroke 1","mn":"ADBE Vector Graphic - Stroke","hd":false},{"ty":"tr","p":{"a":0,"k":[250,252.751],"ix":2},"a":{"a":0,"k":[0,0],"ix":1},"s":{"a":0,"k":[100,100],"ix":3},"r":{"a":0,"k":0,"ix":6},"o":{"a":0,"k":100,"ix":7},"sk":{"a":0,"k":0,"ix":4},"sa":{"a":0,"k":0,"ix":5},"nm":"Transform"}],"nm":"Group 2","np":2,"cix":2,"bm":0,"ix":2,"mn":"ADBE Vector Group","hd":false},{"ty":"gr","it":[{"ind":0,"ty":"sh","ix":1,"ks":{"a":1,"k":[{"i":{"x":0.667,"y":1},"o":{"x":0.333,"y":0},"t":9,"s":[{"i":[[0,0],[0,0]],"o":[[0,0],[0,0]],"v":[[-4.202,0],[4.202,0]],"c":false}]},{"i":{"x":0.667,"y":1},"o":{"x":0.333,"y":0},"t":19,"s":[{"i":[[0,0],[0,0]],"o":[[0,0],[0,0]],"v":[[-4.202,10],[4.202,10]],"c":false}]},{"i":{"x":0.667,"y":1},"o":{"x":0.333,"y":0},"t":30,"s":[{"i":[[0,0],[0,0]],"o":[[0,0],[0,0]],"v":[[-4.202,-13],[4.202,-13]],"c":false}]},{"i":{"x":0.667,"y":1},"o":{"x":0.333,"y":0},"t":41,"s":[{"i":[[0,0],[0,0]],"o":[[0,0],[0,0]],"v":[[-4.202,10],[4.202,10]],"c":false}]},{"t":52,"s":[{"i":[[0,0],[0,0]],"o":[[0,0],[0,0]],"v":[[-4.202,0],[4.202,0]],"c":false}]}],"ix":2},"nm":"Path 1","mn":"ADBE Vector Shape - Group","hd":false},{"ty":"st","c":{"a":0,"k":[0,0,0,1],"ix":3,"x":"var $bm_rt;\n$bm_rt = thisComp.layer('Main Stroke width - Color Ctrl').effect('Highlight 2')('Color');"},"o":{"a":0,"k":100,"ix":4},"w":{"a":0,"k":16,"ix":5,"x":"var $bm_rt;\n$bm_rt = thisComp.layer('Main Stroke width - Color Ctrl').effect('Stroke width')('Slider');"},"lc":2,"lj":2,"bm":0,"nm":"Stroke 1","mn":"ADBE Vector Graphic - Stroke","hd":false},{"ty":"tr","p":{"a":0,"k":[196.6,239.439],"ix":2},"a":{"a":0,"k":[0,0],"ix":1},"s":{"a":0,"k":[100,100],"ix":3},"r":{"a":0,"k":0,"ix":6},"o":{"a":0,"k":100,"ix":7},"sk":{"a":0,"k":0,"ix":4},"sa":{"a":0,"k":0,"ix":5},"nm":"Transform"}],"nm":"Group 5","np":2,"cix":2,"bm":0,"ix":3,"mn":"ADBE Vector Group","hd":false},{"ty":"gr","it":[{"ind":0,"ty":"sh","ix":1,"ks":{"a":1,"k":[{"i":{"x":0.667,"y":1},"o":{"x":0.333,"y":0},"t":9,"s":[{"i":[[0,0],[0,0]],"o":[[0,0],[0,0]],"v":[[-4.202,0],[4.202,0]],"c":false}]},{"i":{"x":0.667,"y":1},"o":{"x":0.333,"y":0},"t":19,"s":[{"i":[[0,0],[0,0]],"o":[[0,0],[0,0]],"v":[[-4.202,10],[4.202,10]],"c":false}]},{"i":{"x":0.667,"y":1},"o":{"x":0.333,"y":0},"t":30,"s":[{"i":[[0,0],[0,0]],"o":[[0,0],[0,0]],"v":[[-4.202,-13],[4.202,-13]],"c":false}]},{"i":{"x":0.667,"y":1},"o":{"x":0.333,"y":0},"t":41,"s":[{"i":[[0,0],[0,0]],"o":[[0,0],[0,0]],"v":[[-4.202,10],[4.202,10]],"c":false}]},{"t":52,"s":[{"i":[[0,0],[0,0]],"o":[[0,0],[0,0]],"v":[[-4.202,0],[4.202,0]],"c":false}]}],"ix":2},"nm":"Path 1","mn":"ADBE Vector Shape - Group","hd":false},{"ty":"st","c":{"a":0,"k":[0,0,0,1],"ix":3,"x":"var $bm_rt;\n$bm_rt = thisComp.layer('Main Stroke width - Color Ctrl').effect('Highlight 2')('Color');"},"o":{"a":0,"k":100,"ix":4},"w":{"a":0,"k":16,"ix":5,"x":"var $bm_rt;\n$bm_rt = thisComp.layer('Main Stroke width - Color Ctrl').effect('Stroke width')('Slider');"},"lc":2,"lj":2,"bm":0,"nm":"Stroke 1","mn":"ADBE Vector Graphic - Stroke","hd":false},{"ty":"tr","p":{"a":0,"k":[303.4,239.439],"ix":2},"a":{"a":0,"k":[0,0],"ix":1},"s":{"a":0,"k":[100,100],"ix":3},"r":{"a":0,"k":0,"ix":6},"o":{"a":0,"k":100,"ix":7},"sk":{"a":0,"k":0,"ix":4},"sa":{"a":0,"k":0,"ix":5},"nm":"Transform"}],"nm":"Group 6","np":2,"cix":2,"bm":0,"ix":4,"mn":"ADBE Vector Group","hd":false},{"ty":"gr","it":[{"ind":0,"ty":"sh","ix":1,"ks":{"a":1,"k":[{"i":{"x":0.667,"y":1},"o":{"x":0.333,"y":0},"t":9,"s":[{"i":[[0,0],[0,0]],"o":[[0,0],[0,0]],"v":[[0,-11.643],[0,11.643]],"c":false}]},{"i":{"x":0.667,"y":1},"o":{"x":0.333,"y":0},"t":19,"s":[{"i":[[0,0],[0,0]],"o":[[0,0],[0,0]],"v":[[0,5.357],[0,21.643]],"c":false}]},{"i":{"x":0.667,"y":1},"o":{"x":0.333,"y":0},"t":30,"s":[{"i":[[0,0],[0,0]],"o":[[0,0],[0,0]],"v":[[0,-24.643],[0,-1.357]],"c":false}]},{"i":{"x":0.667,"y":1},"o":{"x":0.333,"y":0},"t":41,"s":[{"i":[[0,0],[0,0]],"o":[[0,0],[0,0]],"v":[[0,5.357],[0,21.643]],"c":false}]},{"t":52,"s":[{"i":[[0,0],[0,0]],"o":[[0,0],[0,0]],"v":[[0,-11.643],[0,11.643]],"c":false}]}],"ix":2},"nm":"Path 1","mn":"ADBE Vector Shape - Group","hd":false},{"ty":"st","c":{"a":0,"k":[0,0,0,1],"ix":3,"x":"var $bm_rt;\n$bm_rt = thisComp.layer('Main Stroke width - Color Ctrl').effect('Base Color')('Color');"},"o":{"a":0,"k":100,"ix":4},"w":{"a":0,"k":16,"ix":5,"x":"var $bm_rt;\n$bm_rt = thisComp.layer('Main Stroke width - Color Ctrl').effect('Stroke width')('Slider');"},"lc":2,"lj":2,"bm":0,"nm":"Stroke 1","mn":"ADBE Vector Graphic - Stroke","hd":false},{"ty":"tr","p":{"a":0,"k":[287.627,205.787],"ix":2},"a":{"a":0,"k":[0,0],"ix":1},"s":{"a":0,"k":[100,100],"ix":3},"r":{"a":0,"k":0,"ix":6},"o":{"a":0,"k":100,"ix":7},"sk":{"a":0,"k":0,"ix":4},"sa":{"a":0,"k":0,"ix":5},"nm":"Transform"}],"nm":"Group 7","np":2,"cix":2,"bm":0,"ix":5,"mn":"ADBE Vector Group","hd":false},{"ty":"gr","it":[{"ind":0,"ty":"sh","ix":1,"ks":{"a":1,"k":[{"i":{"x":0.667,"y":1},"o":{"x":0.333,"y":0},"t":9,"s":[{"i":[[0,0],[0,0]],"o":[[0,0],[0,0]],"v":[[0,-11.643],[0,11.643]],"c":false}]},{"i":{"x":0.667,"y":1},"o":{"x":0.333,"y":0},"t":19,"s":[{"i":[[0,0],[0,0]],"o":[[0,0],[0,0]],"v":[[0,5.357],[0,21.643]],"c":false}]},{"i":{"x":0.667,"y":1},"o":{"x":0.333,"y":0},"t":30,"s":[{"i":[[0,0],[0,0]],"o":[[0,0],[0,0]],"v":[[0,-24.643],[0,-1.357]],"c":false}]},{"i":{"x":0.667,"y":1},"o":{"x":0.333,"y":0},"t":41,"s":[{"i":[[0,0],[0,0]],"o":[[0,0],[0,0]],"v":[[0,5.357],[0,21.643]],"c":false}]},{"t":52,"s":[{"i":[[0,0],[0,0]],"o":[[0,0],[0,0]],"v":[[0,-11.643],[0,11.643]],"c":false}]}],"ix":2},"nm":"Path 1","mn":"ADBE Vector Shape - Group","hd":false},{"ty":"st","c":{"a":0,"k":[0,0,0,1],"ix":3,"x":"var $bm_rt;\n$bm_rt = thisComp.layer('Main Stroke width - Color Ctrl').effect('Base Color')('Color');"},"o":{"a":0,"k":100,"ix":4},"w":{"a":0,"k":16,"ix":5,"x":"var $bm_rt;\n$bm_rt = thisComp.layer('Main Stroke width - Color Ctrl').effect('Stroke width')('Slider');"},"lc":2,"lj":2,"bm":0,"nm":"Stroke 1","mn":"ADBE Vector Graphic - Stroke","hd":false},{"ty":"tr","p":{"a":0,"k":[212.373,205.787],"ix":2},"a":{"a":0,"k":[0,0],"ix":1},"s":{"a":0,"k":[100,100],"ix":3},"r":{"a":0,"k":0,"ix":6},"o":{"a":0,"k":100,"ix":7},"sk":{"a":0,"k":0,"ix":4},"sa":{"a":0,"k":0,"ix":5},"nm":"Transform"}],"nm":"Group 8","np":2,"cix":2,"bm":0,"ix":6,"mn":"ADBE Vector Group","hd":false},{"ty":"gr","it":[{"ind":0,"ty":"sh","ix":1,"ks":{"a":0,"k":{"i":[[34.935,0],[0,0],[0,34.935],[0,0],[-34.935,0],[0,0],[0,-34.935],[0,0]],"o":[[0,0],[-34.935,0],[0,0],[0,-34.935],[0,0],[34.935,0],[0,0],[0,34.935]],"v":[[23.445,93.554],[-23.445,93.554],[-86.7,30.298],[-86.7,-30.298],[-23.445,-93.554],[23.445,-93.554],[86.7,-30.298],[86.7,30.298]],"c":true},"ix":2},"nm":"Path 1","mn":"ADBE Vector Shape - Group","hd":false},{"ty":"st","c":{"a":0,"k":[0,0,0,1],"ix":3,"x":"var $bm_rt;\n$bm_rt = thisComp.layer('Main Stroke width - Color Ctrl').effect('Base Color')('Color');"},"o":{"a":0,"k":100,"ix":4},"w":{"a":0,"k":16,"ix":5,"x":"var $bm_rt;\n$bm_rt = thisComp.layer('Main Stroke width - Color Ctrl').effect('Stroke width')('Slider');"},"lc":2,"lj":2,"bm":0,"nm":"Stroke 1","mn":"ADBE Vector Graphic - Stroke","hd":false},{"ty":"tr","p":{"a":0,"k":[250,234.851],"ix":2},"a":{"a":0,"k":[0,0],"ix":1},"s":{"a":0,"k":[100,100],"ix":3},"r":{"a":0,"k":0,"ix":6},"o":{"a":0,"k":100,"ix":7},"sk":{"a":0,"k":0,"ix":4},"sa":{"a":0,"k":0,"ix":5},"nm":"Transform"}],"nm":"Group 9","np":2,"cix":2,"bm":0,"ix":7,"mn":"ADBE Vector Group","hd":false}],"ip":0,"op":60,"st":0,"ct":1,"bm":0},{"ddd":0,"ind":3,"ty":4,"nm":"head","parent":2,"sr":1,"ks":{"o":{"a":0,"k":100,"ix":11},"r":{"a":0,"k":0,"ix":10},"p":{"a":0,"k":[250,234.789,0],"ix":2,"l":2},"a":{"a":0,"k":[250,234.789,0],"ix":1,"l":2},"s":{"a":0,"k":[100,100,100],"ix":6,"l":2}},"ao":0,"shapes":[{"ty":"gr","it":[{"ind":0,"ty":"sh","ix":1,"ks":{"a":1,"k":[{"i":{"x":0.667,"y":1},"o":{"x":0.333,"y":0},"t":9,"s":[{"i":[[0,-9.412],[12.9,0],[0,9.412],[-12.9,0]],"o":[[0,9.412],[-12.9,0],[0,-9.412],[12.9,0]],"v":[[23.358,0],[0,17.043],[-23.358,0],[0,-17.043]],"c":true}]},{"i":{"x":0.667,"y":1},"o":{"x":0.333,"y":0},"t":19,"s":[{"i":[[0,-9.412],[12.9,0],[0,9.412],[-12.9,0]],"o":[[0,9.412],[-12.9,0],[0,-9.412],[12.9,0]],"v":[[23.216,9.5],[-0.142,26.543],[-23.5,9.5],[-0.142,-7.543]],"c":true}]},{"i":{"x":0.667,"y":1},"o":{"x":0.333,"y":0},"t":30,"s":[{"i":[[0,-9.412],[12.9,0],[0,9.412],[-12.9,0]],"o":[[0,9.412],[-12.9,0],[0,-9.412],[12.9,0]],"v":[[23.075,-13.5],[-0.284,3.543],[-23.642,-13.5],[-0.284,-30.543]],"c":true}]},{"i":{"x":0.667,"y":1},"o":{"x":0.333,"y":0},"t":41,"s":[{"i":[[0,-9.412],[12.9,0],[0,9.412],[-12.9,0]],"o":[[0,9.412],[-12.9,0],[0,-9.412],[12.9,0]],"v":[[23.216,9.5],[-0.142,26.543],[-23.5,9.5],[-0.142,-7.543]],"c":true}]},{"t":52,"s":[{"i":[[0,-9.412],[12.9,0],[0,9.412],[-12.9,0]],"o":[[0,9.412],[-12.9,0],[0,-9.412],[12.9,0]],"v":[[23.358,0],[0,17.043],[-23.358,0],[0,-17.043]],"c":true}]}],"ix":2},"nm":"Path 1","mn":"ADBE Vector Shape - Group","hd":false},{"ty":"fl","c":{"a":0,"k":[0.831372559071,0.419607847929,0.360784322023,1],"ix":4},"o":{"a":0,"k":100,"ix":5},"r":1,"bm":0,"nm":"Fill 1","mn":"ADBE Vector Graphic - Fill","hd":false},{"ty":"tr","p":{"a":0,"k":[250,252.762],"ix":2},"a":{"a":0,"k":[0,0],"ix":1},"s":{"a":0,"k":[100,100],"ix":3},"r":{"a":0,"k":0,"ix":6},"o":{"a":0,"k":100,"ix":7},"sk":{"a":0,"k":0,"ix":4},"sa":{"a":0,"k":0,"ix":5},"nm":"Transform"}],"nm":"Group 1","np":2,"cix":2,"bm":0,"ix":1,"mn":"ADBE Vector Group","hd":false},{"ty":"gr","it":[{"ind":0,"ty":"sh","ix":1,"ks":{"a":1,"k":[{"i":{"x":0.667,"y":1},"o":{"x":0.333,"y":0},"t":9,"s":[{"i":[[0,-34.416],[0,0],[14.739,0],[0,0],[10.784,8.376],[0,0],[-34.534,0]],"o":[[0,0],[-10.784,8.376],[0,0],[-14.739,0],[0,0],[0,-34.416],[34.534,0]],"v":[[62.535,24.339],[62.535,24.597],[23.441,37.969],[-23.441,37.969],[-62.535,24.597],[-62.535,24.339],[0,-37.969]],"c":true}]},{"i":{"x":0.667,"y":1},"o":{"x":0.333,"y":0},"t":19,"s":[{"i":[[0,-34.416],[0,0],[14.739,0],[0,0],[10.784,8.376],[0,0],[-34.534,0]],"o":[[0,0],[-10.784,8.376],[0,0],[-14.739,0],[0,0],[0,-34.416],[34.534,0]],"v":[[62.535,24.339],[62.535,24.597],[23.441,37.969],[-23.441,37.969],[-62.535,24.597],[-62.535,24.339],[-0.142,-28.469]],"c":true}]},{"i":{"x":0.667,"y":1},"o":{"x":0.333,"y":0},"t":30,"s":[{"i":[[0,-34.416],[0,0],[14.739,0],[0,0],[10.784,8.376],[0,0],[-34.534,0]],"o":[[0,0],[-10.784,8.376],[0,0],[-14.739,0],[0,0],[0,-34.416],[34.534,0]],"v":[[62.535,24.339],[62.535,24.597],[23.441,37.969],[-23.441,37.969],[-62.535,24.597],[-62.535,24.339],[-0.284,-51.469]],"c":true}]},{"i":{"x":0.667,"y":1},"o":{"x":0.333,"y":0},"t":41,"s":[{"i":[[0,-34.416],[0,0],[14.739,0],[0,0],[10.784,8.376],[0,0],[-34.534,0]],"o":[[0,0],[-10.784,8.376],[0,0],[-14.739,0],[0,0],[0,-34.416],[34.534,0]],"v":[[62.535,24.339],[62.535,24.597],[23.441,37.969],[-23.441,37.969],[-62.535,24.597],[-62.535,24.339],[-0.142,-28.469]],"c":true}]},{"t":52,"s":[{"i":[[0,-34.416],[0,0],[14.739,0],[0,0],[10.784,8.376],[0,0],[-34.534,0]],"o":[[0,0],[-10.784,8.376],[0,0],[-14.739,0],[0,0],[0,-34.416],[34.534,0]],"v":[[62.535,24.339],[62.535,24.597],[23.441,37.969],[-23.441,37.969],[-62.535,24.597],[-62.535,24.339],[0,-37.969]],"c":true}]}],"ix":2},"nm":"Path 1","mn":"ADBE Vector Shape - Group","hd":false},{"ty":"fl","c":{"a":0,"k":[1,1,1,1],"ix":4},"o":{"a":0,"k":100,"ix":5},"r":1,"bm":0,"nm":"Fill 1","mn":"ADBE Vector Graphic - Fill","hd":false},{"ty":"tr","p":{"a":0,"k":[250,290.756],"ix":2},"a":{"a":0,"k":[0,0],"ix":1},"s":{"a":0,"k":[100,100],"ix":3},"r":{"a":0,"k":0,"ix":6},"o":{"a":0,"k":100,"ix":7},"sk":{"a":0,"k":0,"ix":4},"sa":{"a":0,"k":0,"ix":5},"nm":"Transform"}],"nm":"Group 2","np":2,"cix":2,"bm":0,"ix":2,"mn":"ADBE Vector Group","hd":false},{"ty":"gr","it":[{"ind":0,"ty":"sh","ix":1,"ks":{"a":0,"k":{"i":[[35.082,0],[0,0],[0,35.082],[0,0],[-35.082,0],[0,0],[0,-35.082],[0,0]],"o":[[0,0],[-35.082,0],[0,0],[0,-35.082],[0,0],[35.082,0],[0,0],[0,35.082]],"v":[[23.554,93.936],[-23.554,93.936],[-87.075,30.414],[-87.075,-30.414],[-23.554,-93.936],[23.554,-93.936],[87.075,-30.414],[87.075,30.414]],"c":true},"ix":2},"nm":"Path 1","mn":"ADBE Vector Shape - Group","hd":false},{"ty":"fl","c":{"a":0,"k":[0.96862745285,0.690196096897,0.450980395079,1],"ix":4},"o":{"a":0,"k":100,"ix":5},"r":1,"bm":0,"nm":"Fill 1","mn":"ADBE Vector Graphic - Fill","hd":false},{"ty":"tr","p":{"a":0,"k":[250,234.789],"ix":2},"a":{"a":0,"k":[0,0],"ix":1},"s":{"a":0,"k":[100,100],"ix":3},"r":{"a":0,"k":0,"ix":6},"o":{"a":0,"k":100,"ix":7},"sk":{"a":0,"k":0,"ix":4},"sa":{"a":0,"k":0,"ix":5},"nm":"Transform"}],"nm":"Group 3","np":2,"cix":2,"bm":0,"ix":3,"mn":"ADBE Vector Group","hd":false}],"ip":0,"op":60,"st":0,"ct":1,"bm":0},{"ddd":0,"ind":4,"ty":4,"nm":"hornL","parent":2,"sr":1,"ks":{"o":{"a":0,"k":100,"ix":11},"r":{"a":1,"k":[{"i":{"x":[0.667],"y":[1]},"o":{"x":[0.333],"y":[0]},"t":9,"s":[0]},{"i":{"x":[0.667],"y":[1]},"o":{"x":[0.333],"y":[0]},"t":19,"s":[6.471]},{"i":{"x":[0.667],"y":[1]},"o":{"x":[0.333],"y":[0]},"t":30,"s":[-12.133]},{"i":{"x":[0.667],"y":[1]},"o":{"x":[0.333],"y":[0]},"t":41,"s":[6.471]},{"t":52,"s":[0]}],"ix":10},"p":{"a":0,"k":[198.242,146.573,0],"ix":2,"l":2},"a":{"a":0,"k":[198.242,146.573,0],"ix":1,"l":2},"s":{"a":0,"k":[100,100,100],"ix":6,"l":2}},"ao":0,"shapes":[{"ty":"gr","it":[{"ind":0,"ty":"sh","ix":1,"ks":{"a":0,"k":{"i":[[0,0],[0,0],[0,0]],"o":[[0,0],[0,0],[0,0]],"v":[[10.147,-32.286],[-10.147,-20.197],[-10.147,32.286]],"c":false},"ix":2},"nm":"Path 1","mn":"ADBE Vector Shape - Group","hd":false},{"ty":"st","c":{"a":0,"k":[0,0,0,1],"ix":3,"x":"var $bm_rt;\n$bm_rt = thisComp.layer('Main Stroke width - Color Ctrl').effect('Highlight 3')('Color');"},"o":{"a":0,"k":100,"ix":4},"w":{"a":0,"k":16,"ix":5,"x":"var $bm_rt;\n$bm_rt = thisComp.layer('Main Stroke width - Color Ctrl').effect('Stroke width')('Slider');"},"lc":2,"lj":2,"bm":0,"nm":"Stroke 1","mn":"ADBE Vector Graphic - Stroke","hd":false},{"ty":"tr","p":{"a":0,"k":[207.688,110.786],"ix":2},"a":{"a":0,"k":[0,0],"ix":1},"s":{"a":0,"k":[100,100],"ix":3},"r":{"a":0,"k":0,"ix":6},"o":{"a":0,"k":100,"ix":7},"sk":{"a":0,"k":0,"ix":4},"sa":{"a":0,"k":0,"ix":5},"nm":"Transform"}],"nm":"Group 1","np":2,"cix":2,"bm":0,"ix":1,"mn":"ADBE Vector Group","hd":false},{"ty":"gr","it":[{"ind":0,"ty":"sh","ix":1,"ks":{"a":0,"k":{"i":[[0,0],[0,0],[0,0]],"o":[[0,0],[0,0],[0,0]],"v":[[24.381,9.694],[-0.054,9.694],[-24.381,-9.694]],"c":false},"ix":2},"nm":"Path 1","mn":"ADBE Vector Shape - Group","hd":false},{"ty":"st","c":{"a":0,"k":[0,0,0,1],"ix":3,"x":"var $bm_rt;\n$bm_rt = thisComp.layer('Main Stroke width - Color Ctrl').effect('Highlight 3')('Color');"},"o":{"a":0,"k":100,"ix":4},"w":{"a":0,"k":16,"ix":5,"x":"var $bm_rt;\n$bm_rt = thisComp.layer('Main Stroke width - Color Ctrl').effect('Stroke width')('Slider');"},"lc":2,"lj":2,"bm":0,"nm":"Stroke 1","mn":"ADBE Vector Graphic - Stroke","hd":false},{"ty":"tr","p":{"a":0,"k":[171.013,96.981],"ix":2},"a":{"a":0,"k":[0,0],"ix":1},"s":{"a":0,"k":[100,100],"ix":3},"r":{"a":0,"k":0,"ix":6},"o":{"a":0,"k":100,"ix":7},"sk":{"a":0,"k":0,"ix":4},"sa":{"a":0,"k":0,"ix":5},"nm":"Transform"}],"nm":"Group 2","np":2,"cix":2,"bm":0,"ix":2,"mn":"ADBE Vector Group","hd":false},{"ty":"gr","it":[{"ind":0,"ty":"sh","ix":1,"ks":{"a":0,"k":{"i":[[0,0],[0,0],[0,0]],"o":[[0,0],[0,0],[0,0]],"v":[[-16.737,5.958],[1.029,5.958],[16.737,-5.958]],"c":false},"ix":2},"nm":"Path 1","mn":"ADBE Vector Shape - Group","hd":false},{"ty":"st","c":{"a":0,"k":[0,0,0,1],"ix":3,"x":"var $bm_rt;\n$bm_rt = thisComp.layer('Main Stroke width - Color Ctrl').effect('Highlight 3')('Color');"},"o":{"a":0,"k":100,"ix":4},"w":{"a":0,"k":16,"ix":5,"x":"var $bm_rt;\n$bm_rt = thisComp.layer('Main Stroke width - Color Ctrl').effect('Stroke width')('Slider');"},"lc":2,"lj":2,"bm":0,"nm":"Stroke 1","mn":"ADBE Vector Graphic - Stroke","hd":false},{"ty":"tr","p":{"a":0,"k":[218.115,107.327],"ix":2},"a":{"a":0,"k":[0,0],"ix":1},"s":{"a":0,"k":[100,100],"ix":3},"r":{"a":0,"k":0,"ix":6},"o":{"a":0,"k":100,"ix":7},"sk":{"a":0,"k":0,"ix":4},"sa":{"a":0,"k":0,"ix":5},"nm":"Transform"}],"nm":"Group 3","np":2,"cix":2,"bm":0,"ix":3,"mn":"ADBE Vector Group","hd":false},{"ty":"gr","it":[{"ind":0,"ty":"sh","ix":1,"ks":{"a":0,"k":{"i":[[0,0],[0,0]],"o":[[0,0],[0,0]],"v":[[-4.499,7.238],[4.499,-7.238]],"c":false},"ix":2},"nm":"Path 1","mn":"ADBE Vector Shape - Group","hd":false},{"ty":"st","c":{"a":0,"k":[0,0,0,1],"ix":3,"x":"var $bm_rt;\n$bm_rt = thisComp.layer('Main Stroke width - Color Ctrl').effect('Highlight 3')('Color');"},"o":{"a":0,"k":100,"ix":4},"w":{"a":0,"k":16,"ix":5,"x":"var $bm_rt;\n$bm_rt = thisComp.layer('Main Stroke width - Color Ctrl').effect('Stroke width')('Slider');"},"lc":2,"lj":2,"bm":0,"nm":"Stroke 1","mn":"ADBE Vector Graphic - Stroke","hd":false},{"ty":"tr","p":{"a":0,"k":[166.514,88.809],"ix":2},"a":{"a":0,"k":[0,0],"ix":1},"s":{"a":0,"k":[100,100],"ix":3},"r":{"a":0,"k":0,"ix":6},"o":{"a":0,"k":100,"ix":7},"sk":{"a":0,"k":0,"ix":4},"sa":{"a":0,"k":0,"ix":5},"nm":"Transform"}],"nm":"Group 4","np":2,"cix":2,"bm":0,"ix":4,"mn":"ADBE Vector Group","hd":false}],"ip":0,"op":60,"st":0,"ct":1,"bm":0},{"ddd":0,"ind":5,"ty":4,"nm":"hornR","parent":2,"sr":1,"ks":{"o":{"a":0,"k":100,"ix":11},"r":{"a":1,"k":[{"i":{"x":[0.667],"y":[1]},"o":{"x":[0.333],"y":[0]},"t":9,"s":[0]},{"i":{"x":[0.667],"y":[1]},"o":{"x":[0.333],"y":[0]},"t":19,"s":[-5.661]},{"i":{"x":[0.667],"y":[1]},"o":{"x":[0.333],"y":[0]},"t":30,"s":[11.03]},{"i":{"x":[0.667],"y":[1]},"o":{"x":[0.333],"y":[0]},"t":41,"s":[-5.661]},{"t":52,"s":[0]}],"ix":10},"p":{"a":0,"k":[300.758,148.286,0],"ix":2,"l":2},"a":{"a":0,"k":[300.758,148.286,0],"ix":1,"l":2},"s":{"a":0,"k":[100,100,100],"ix":6,"l":2}},"ao":0,"shapes":[{"ty":"gr","it":[{"ind":0,"ty":"sh","ix":1,"ks":{"a":0,"k":{"i":[[0,0],[0,0],[0,0]],"o":[[0,0],[0,0],[0,0]],"v":[[-10.147,-32.286],[10.147,-20.197],[10.147,32.286]],"c":false},"ix":2},"nm":"Path 1","mn":"ADBE Vector Shape - Group","hd":false},{"ty":"st","c":{"a":0,"k":[0,0,0,1],"ix":3,"x":"var $bm_rt;\n$bm_rt = thisComp.layer('Main Stroke width - Color Ctrl').effect('Highlight 3')('Color');"},"o":{"a":0,"k":100,"ix":4},"w":{"a":0,"k":16,"ix":5,"x":"var $bm_rt;\n$bm_rt = thisComp.layer('Main Stroke width - Color Ctrl').effect('Stroke width')('Slider');"},"lc":2,"lj":2,"bm":0,"nm":"Stroke 1","mn":"ADBE Vector Graphic - Stroke","hd":false},{"ty":"tr","p":{"a":0,"k":[292.312,110.786],"ix":2},"a":{"a":0,"k":[0,0],"ix":1},"s":{"a":0,"k":[100,100],"ix":3},"r":{"a":0,"k":0,"ix":6},"o":{"a":0,"k":100,"ix":7},"sk":{"a":0,"k":0,"ix":4},"sa":{"a":0,"k":0,"ix":5},"nm":"Transform"}],"nm":"Group 1","np":2,"cix":2,"bm":0,"ix":1,"mn":"ADBE Vector Group","hd":false},{"ty":"gr","it":[{"ind":0,"ty":"sh","ix":1,"ks":{"a":0,"k":{"i":[[0,0],[0,0],[0,0]],"o":[[0,0],[0,0],[0,0]],"v":[[-24.381,9.694],[0.054,9.694],[24.381,-9.694]],"c":false},"ix":2},"nm":"Path 1","mn":"ADBE Vector Shape - Group","hd":false},{"ty":"st","c":{"a":0,"k":[0,0,0,1],"ix":3,"x":"var $bm_rt;\n$bm_rt = thisComp.layer('Main Stroke width - Color Ctrl').effect('Highlight 3')('Color');"},"o":{"a":0,"k":100,"ix":4},"w":{"a":0,"k":16,"ix":5,"x":"var $bm_rt;\n$bm_rt = thisComp.layer('Main Stroke width - Color Ctrl').effect('Stroke width')('Slider');"},"lc":2,"lj":2,"bm":0,"nm":"Stroke 1","mn":"ADBE Vector Graphic - Stroke","hd":false},{"ty":"tr","p":{"a":0,"k":[328.987,96.981],"ix":2},"a":{"a":0,"k":[0,0],"ix":1},"s":{"a":0,"k":[100,100],"ix":3},"r":{"a":0,"k":0,"ix":6},"o":{"a":0,"k":100,"ix":7},"sk":{"a":0,"k":0,"ix":4},"sa":{"a":0,"k":0,"ix":5},"nm":"Transform"}],"nm":"Group 2","np":2,"cix":2,"bm":0,"ix":2,"mn":"ADBE Vector Group","hd":false},{"ty":"gr","it":[{"ind":0,"ty":"sh","ix":1,"ks":{"a":0,"k":{"i":[[0,0],[0,0],[0,0]],"o":[[0,0],[0,0],[0,0]],"v":[[16.737,5.958],[-1.029,5.958],[-16.737,-5.958]],"c":false},"ix":2},"nm":"Path 1","mn":"ADBE Vector Shape - Group","hd":false},{"ty":"st","c":{"a":0,"k":[0,0,0,1],"ix":3,"x":"var $bm_rt;\n$bm_rt = thisComp.layer('Main Stroke width - Color Ctrl').effect('Highlight 3')('Color');"},"o":{"a":0,"k":100,"ix":4},"w":{"a":0,"k":16,"ix":5,"x":"var $bm_rt;\n$bm_rt = thisComp.layer('Main Stroke width - Color Ctrl').effect('Stroke width')('Slider');"},"lc":2,"lj":2,"bm":0,"nm":"Stroke 1","mn":"ADBE Vector Graphic - Stroke","hd":false},{"ty":"tr","p":{"a":0,"k":[281.885,107.327],"ix":2},"a":{"a":0,"k":[0,0],"ix":1},"s":{"a":0,"k":[100,100],"ix":3},"r":{"a":0,"k":0,"ix":6},"o":{"a":0,"k":100,"ix":7},"sk":{"a":0,"k":0,"ix":4},"sa":{"a":0,"k":0,"ix":5},"nm":"Transform"}],"nm":"Group 3","np":2,"cix":2,"bm":0,"ix":3,"mn":"ADBE Vector Group","hd":false},{"ty":"gr","it":[{"ind":0,"ty":"sh","ix":1,"ks":{"a":0,"k":{"i":[[0,0],[0,0]],"o":[[0,0],[0,0]],"v":[[4.499,7.238],[-4.499,-7.238]],"c":false},"ix":2},"nm":"Path 1","mn":"ADBE Vector Shape - Group","hd":false},{"ty":"st","c":{"a":0,"k":[0,0,0,1],"ix":3,"x":"var $bm_rt;\n$bm_rt = thisComp.layer('Main Stroke width - Color Ctrl').effect('Highlight 3')('Color');"},"o":{"a":0,"k":100,"ix":4},"w":{"a":0,"k":16,"ix":5,"x":"var $bm_rt;\n$bm_rt = thisComp.layer('Main Stroke width - Color Ctrl').effect('Stroke width')('Slider');"},"lc":2,"lj":2,"bm":0,"nm":"Stroke 1","mn":"ADBE Vector Graphic - Stroke","hd":false},{"ty":"tr","p":{"a":0,"k":[333.486,88.809],"ix":2},"a":{"a":0,"k":[0,0],"ix":1},"s":{"a":0,"k":[100,100],"ix":3},"r":{"a":0,"k":0,"ix":6},"o":{"a":0,"k":100,"ix":7},"sk":{"a":0,"k":0,"ix":4},"sa":{"a":0,"k":0,"ix":5},"nm":"Transform"}],"nm":"Group 4","np":2,"cix":2,"bm":0,"ix":4,"mn":"ADBE Vector Group","hd":false}],"ip":0,"op":60,"st":0,"ct":1,"bm":0},{"ddd":0,"ind":6,"ty":4,"nm":"earL","parent":2,"sr":1,"ks":{"o":{"a":0,"k":100,"ix":11},"r":{"a":0,"k":0,"ix":10},"p":{"a":0,"k":[187.2,190.951,0],"ix":2,"l":2},"a":{"a":0,"k":[33.254,27.011,0],"ix":1,"l":2},"s":{"a":0,"k":[100,100,100],"ix":6,"l":2}},"ao":0,"shapes":[{"ty":"gr","it":[{"ind":0,"ty":"sh","ix":1,"ks":{"a":1,"k":[{"i":{"x":0.667,"y":1},"o":{"x":0.333,"y":0},"t":9,"s":[{"i":[[0,0],[10.92,0],[0,0],[0,0],[-21.302,0],[0,0]],"o":[[-7.017,-7.294],[0,0],[0,0],[0,21.307],[0,0],[0,0]],"v":[[33.254,-15.178],[5.457,-27.011],[-33.254,-27.011],[-33.254,-11.568],[5.316,27.011],[7.144,27.011]],"c":false}]},{"i":{"x":0.667,"y":1},"o":{"x":0.333,"y":0},"t":19,"s":[{"i":[[0,0],[10.845,3.45],[0,0],[0,0],[-21.302,0],[0,0]],"o":[[-4.7,-4.133],[0,0],[0,0],[-4.12,20.905],[0,0],[0,0]],"v":[[33.254,-15.178],[10.708,-31.761],[-27.272,-41.247],[-30.258,-24.095],[5.316,27.011],[7.144,27.011]],"c":false}]},{"i":{"x":0.667,"y":1},"o":{"x":0.333,"y":0},"t":30,"s":[{"i":[[0,0],[17.944,-10.739],[0,0],[0,0],[-21.263,15.387],[0,0]],"o":[[-9.7,-9.924],[0,0],[0,0],[11.526,17.92],[0,0],[0,0]],"v":[[33.254,-15.178],[-20.89,-16.862],[-51.948,5.579],[-45.094,17.067],[5.316,27.011],[7.144,27.011]],"c":false}]},{"i":{"x":0.667,"y":1},"o":{"x":0.333,"y":0},"t":41,"s":[{"i":[[0,0],[10.845,3.45],[0,0],[0,0],[-21.302,0],[0,0]],"o":[[-4.7,-4.133],[0,0],[0,0],[-4.12,20.905],[0,0],[0,0]],"v":[[33.254,-15.178],[10.708,-31.761],[-27.272,-41.247],[-30.258,-24.095],[5.316,27.011],[7.144,27.011]],"c":false}]},{"t":52,"s":[{"i":[[0,0],[10.92,0],[0,0],[0,0],[-21.302,0],[0,0]],"o":[[-7.017,-7.294],[0,0],[0,0],[0,21.307],[0,0],[0,0]],"v":[[33.254,-15.178],[5.457,-27.011],[-33.254,-27.011],[-33.254,-11.568],[5.316,27.011],[7.144,27.011]],"c":false}]}],"ix":2},"nm":"Path 1","mn":"ADBE Vector Shape - Group","hd":false},{"ty":"st","c":{"a":0,"k":[0.20000000298,0.800000011921,0.800000011921,1],"ix":3,"x":"var $bm_rt;\n$bm_rt = thisComp.layer('Main Stroke width - Color Ctrl').effect('Base Color')('Color');"},"o":{"a":0,"k":100,"ix":4},"w":{"a":0,"k":16,"ix":5,"x":"var $bm_rt;\n$bm_rt = thisComp.layer('Main Stroke width - Color Ctrl').effect('Stroke width')('Slider');"},"lc":2,"lj":2,"bm":0,"nm":"Stroke 1","mn":"ADBE Vector Graphic - Stroke","hd":false},{"ty":"tr","p":{"a":0,"k":[0,0],"ix":2},"a":{"a":0,"k":[0,0],"ix":1},"s":{"a":0,"k":[100,100],"ix":3},"r":{"a":0,"k":0,"ix":6},"o":{"a":0,"k":100,"ix":7},"sk":{"a":0,"k":0,"ix":4},"sa":{"a":0,"k":0,"ix":5},"nm":"Transform"}],"nm":"Group 1","np":2,"cix":2,"bm":0,"ix":1,"mn":"ADBE Vector Group","hd":false}],"ip":0,"op":60,"st":0,"ct":1,"bm":0},{"ddd":0,"ind":7,"ty":4,"nm":"ear-L","parent":6,"sr":1,"ks":{"o":{"a":0,"k":100,"ix":11},"r":{"a":0,"k":0,"ix":10},"p":{"a":0,"k":[4.995,-0.351,0],"ix":2,"l":2},"a":{"a":0,"k":[0,0,0],"ix":1,"l":2},"s":{"a":0,"k":[100,100,100],"ix":6,"l":2}},"ao":0,"shapes":[{"ty":"gr","it":[{"ind":0,"ty":"sh","ix":1,"ks":{"a":1,"k":[{"i":{"x":0.667,"y":1},"o":{"x":0.333,"y":0},"t":9,"s":[{"i":[[-21.394,0],[0,0],[0,0],[21.394,0],[0,0],[0,0]],"o":[[0,0],[0,0],[0,-21.394],[0,0],[0,0],[0,21.394]],"v":[[-0.071,27.121],[38.808,27.121],[38.808,11.616],[0.071,-27.121],[-38.808,-27.121],[-38.808,-11.616]],"c":true}]},{"i":{"x":0.667,"y":1},"o":{"x":0.333,"y":0},"t":19,"s":[{"i":[[-20.506,-6.098],[0,0],[0,0],[20.506,6.098],[0,0],[0,0]],"o":[[0,0],[0,0],[6.098,-20.506],[0,0],[0,0],[-6.098,20.506]],"v":[[-9.298,23.976],[27.968,35.057],[32.387,20.195],[6.298,-27.976],[-30.968,-39.057],[-35.387,-24.195]],"c":true}]},{"i":{"x":0.667,"y":1},"o":{"x":0.333,"y":0},"t":30,"s":[{"i":[[-17.444,12.385],[0,0],[0,0],[17.444,-12.385],[0,0],[0,0]],"o":[[0,0],[0,0],[-12.385,-17.444],[0,0],[0,0],[12.385,17.444]],"v":[[6.143,27.155],[37.844,4.648],[28.868,-7.995],[-25.143,-17.155],[-56.844,5.352],[-47.868,17.995]],"c":true}]},{"i":{"x":0.667,"y":1},"o":{"x":0.333,"y":0},"t":41,"s":[{"i":[[-20.506,-6.098],[0,0],[0,0],[20.506,6.098],[0,0],[0,0]],"o":[[0,0],[0,0],[6.098,-20.506],[0,0],[0,0],[-6.098,20.506]],"v":[[-9.298,23.976],[27.968,35.057],[32.387,20.195],[6.298,-27.976],[-30.968,-39.057],[-35.387,-24.195]],"c":true}]},{"t":52,"s":[{"i":[[-21.394,0],[0,0],[0,0],[21.394,0],[0,0],[0,0]],"o":[[0,0],[0,0],[0,-21.394],[0,0],[0,0],[0,21.394]],"v":[[-0.071,27.121],[38.808,27.121],[38.808,11.616],[0.071,-27.121],[-38.808,-27.121],[-38.808,-11.616]],"c":true}]}],"ix":2},"nm":"Path 1","mn":"ADBE Vector Shape - Group","hd":false},{"ty":"fl","c":{"a":0,"k":[0.831372559071,0.419607847929,0.360784322023,1],"ix":4},"o":{"a":0,"k":100,"ix":5},"r":1,"bm":0,"nm":"Fill 1","mn":"ADBE Vector Graphic - Fill","hd":false},{"ty":"tr","p":{"a":0,"k":[0,0],"ix":2},"a":{"a":0,"k":[0,0],"ix":1},"s":{"a":0,"k":[100,100],"ix":3},"r":{"a":0,"k":0,"ix":6},"o":{"a":0,"k":100,"ix":7},"sk":{"a":0,"k":0,"ix":4},"sa":{"a":0,"k":0,"ix":5},"nm":"Transform"}],"nm":"Group 1","np":2,"cix":2,"bm":0,"ix":1,"mn":"ADBE Vector Group","hd":false}],"ip":0,"op":60,"st":0,"ct":1,"bm":0},{"ddd":0,"ind":8,"ty":4,"nm":"earR","parent":2,"sr":1,"ks":{"o":{"a":0,"k":100,"ix":11},"r":{"a":0,"k":0,"ix":10},"p":{"a":0,"k":[312.829,190.951,0],"ix":2,"l":2},"a":{"a":0,"k":[-33.239,27.011,0],"ix":1,"l":2},"s":{"a":0,"k":[100,100,100],"ix":6,"l":2}},"ao":0,"shapes":[{"ty":"gr","it":[{"ind":0,"ty":"sh","ix":1,"ks":{"a":1,"k":[{"i":{"x":0.667,"y":1},"o":{"x":0.333,"y":0},"t":9,"s":[{"i":[[0,0],[-10.904,0],[0,0],[0,0],[21.302,0],[0,0]],"o":[[7.015,-7.276],[0,0],[0,0],[0,21.307],[0,0],[0,0]],"v":[[-33.239,-15.209],[-5.472,-27.011],[33.239,-27.011],[33.239,-11.568],[-5.331,27.011],[-6.548,27.011]],"c":false}]},{"i":{"x":0.667,"y":1},"o":{"x":0.333,"y":0},"t":19,"s":[{"i":[[0,0],[-11.47,4.835],[0,0],[0,0],[21.302,0],[0,0]],"o":[[3.171,-4.602],[0,0],[0,0],[3.481,21.021],[0,0],[0,0]],"v":[[-33.239,-15.209],[-10.098,-32.147],[28.593,-41.471],[30.616,-23.236],[-5.331,27.011],[-6.548,27.011]],"c":false}]},{"i":{"x":0.667,"y":1},"o":{"x":0.333,"y":0},"t":30,"s":[{"i":[[0,0],[-13.233,-4.416],[0,0],[0,0],[20.763,11.887],[0,0]],"o":[[11.671,-6.893],[0,0],[0,0],[-8.774,18.93],[0,0],[0,0]],"v":[[-33.239,-15.209],[7.665,-20.186],[44.48,0.282],[39.706,14.968],[-5.331,27.011],[-6.548,27.011]],"c":false}]},{"i":{"x":0.667,"y":1},"o":{"x":0.333,"y":0},"t":41,"s":[{"i":[[0,0],[-11.47,4.835],[0,0],[0,0],[21.302,0],[0,0]],"o":[[3.171,-4.602],[0,0],[0,0],[3.481,21.021],[0,0],[0,0]],"v":[[-33.239,-15.209],[-10.098,-32.147],[28.593,-41.471],[30.616,-23.236],[-5.331,27.011],[-6.548,27.011]],"c":false}]},{"t":52,"s":[{"i":[[0,0],[-10.904,0],[0,0],[0,0],[21.302,0],[0,0]],"o":[[7.015,-7.276],[0,0],[0,0],[0,21.307],[0,0],[0,0]],"v":[[-33.239,-15.209],[-5.472,-27.011],[33.239,-27.011],[33.239,-11.568],[-5.331,27.011],[-6.548,27.011]],"c":false}]}],"ix":2},"nm":"Path 1","mn":"ADBE Vector Shape - Group","hd":false},{"ty":"st","c":{"a":0,"k":[0.20000000298,0.800000011921,0.800000011921,1],"ix":3,"x":"var $bm_rt;\n$bm_rt = thisComp.layer('Main Stroke width - Color Ctrl').effect('Base Color')('Color');"},"o":{"a":0,"k":100,"ix":4},"w":{"a":0,"k":16,"ix":5,"x":"var $bm_rt;\n$bm_rt = thisComp.layer('Main Stroke width - Color Ctrl').effect('Stroke width')('Slider');"},"lc":2,"lj":2,"bm":0,"nm":"Stroke 1","mn":"ADBE Vector Graphic - Stroke","hd":false},{"ty":"tr","p":{"a":0,"k":[0,0],"ix":2},"a":{"a":0,"k":[0,0],"ix":1},"s":{"a":0,"k":[100,100],"ix":3},"r":{"a":0,"k":0,"ix":6},"o":{"a":0,"k":100,"ix":7},"sk":{"a":0,"k":0,"ix":4},"sa":{"a":0,"k":0,"ix":5},"nm":"Transform"}],"nm":"Group 1","np":2,"cix":2,"bm":0,"ix":1,"mn":"ADBE Vector Group","hd":false}],"ip":0,"op":60,"st":0,"ct":1,"bm":0},{"ddd":0,"ind":9,"ty":4,"nm":"ear-R","parent":8,"sr":1,"ks":{"o":{"a":0,"k":100,"ix":11},"r":{"a":0,"k":0,"ix":10},"p":{"a":0,"k":[-5.01,-0.351,0],"ix":2,"l":2},"a":{"a":0,"k":[0,0,0],"ix":1,"l":2},"s":{"a":0,"k":[100,100,100],"ix":6,"l":2}},"ao":0,"shapes":[{"ty":"gr","it":[{"ind":0,"ty":"sh","ix":1,"ks":{"a":1,"k":[{"i":{"x":0.667,"y":1},"o":{"x":0.333,"y":0},"t":9,"s":[{"i":[[21.394,0],[0,0],[0,0],[-21.394,0],[0,0],[0,0]],"o":[[0,0],[0,0],[0,-21.394],[0,0],[0,0],[0,21.394]],"v":[[0.071,27.121],[-38.808,27.121],[-38.808,11.616],[-0.071,-27.121],[38.808,-27.121],[38.808,-11.616]],"c":true}]},{"i":{"x":0.667,"y":1},"o":{"x":0.333,"y":0},"t":19,"s":[{"i":[[20.594,-5.795],[0,0],[0,0],[-20.594,5.795],[0,0],[0,0]],"o":[[0,0],[0,0],[-5.795,-20.594],[0,0],[0,0],[5.795,20.594]],"v":[[7.915,24.088],[-29.51,34.62],[-33.71,19.693],[-6.915,-28.088],[30.51,-38.62],[34.71,-23.693]],"c":true}]},{"i":{"x":0.667,"y":1},"o":{"x":0.333,"y":0},"t":30,"s":[{"i":[[18.344,11.009],[0,0],[0,0],[-18.344,-11.009],[0,0],[0,0]],"o":[[0,0],[0,0],[11.009,-18.344],[0,0],[0,0],[-11.009,18.344]],"v":[[-8.896,29.291],[-42.232,9.285],[-34.252,-4.01],[18.896,-17.291],[52.232,2.715],[44.252,16.01]],"c":true}]},{"i":{"x":0.667,"y":1},"o":{"x":0.333,"y":0},"t":41,"s":[{"i":[[20.62,-5.7],[0,0],[0,0],[-20.62,5.7],[0,0],[0,0]],"o":[[0,0],[0,0],[-5.7,-20.62],[0,0],[0,0],[5.7,20.62]],"v":[[7.294,22.622],[-30.179,32.981],[-34.31,18.036],[-7.294,-29.622],[30.179,-39.981],[34.31,-25.036]],"c":true}]},{"t":52,"s":[{"i":[[21.394,0],[0,0],[0,0],[-21.394,0],[0,0],[0,0]],"o":[[0,0],[0,0],[0,-21.394],[0,0],[0,0],[0,21.394]],"v":[[0.071,27.121],[-38.808,27.121],[-38.808,11.616],[-0.071,-27.121],[38.808,-27.121],[38.808,-11.616]],"c":true}]}],"ix":2},"nm":"Path 1","mn":"ADBE Vector Shape - Group","hd":false},{"ty":"fl","c":{"a":0,"k":[0.831372559071,0.419607847929,0.360784322023,1],"ix":4},"o":{"a":0,"k":100,"ix":5},"r":1,"bm":0,"nm":"Fill 1","mn":"ADBE Vector Graphic - Fill","hd":false},{"ty":"tr","p":{"a":0,"k":[0,0],"ix":2},"a":{"a":0,"k":[0,0],"ix":1},"s":{"a":0,"k":[100,100],"ix":3},"r":{"a":0,"k":0,"ix":6},"o":{"a":0,"k":100,"ix":7},"sk":{"a":0,"k":0,"ix":4},"sa":{"a":0,"k":0,"ix":5},"nm":"Transform"}],"nm":"Group 1","np":2,"cix":2,"bm":0,"ix":1,"mn":"ADBE Vector Group","hd":false}],"ip":0,"op":60,"st":0,"ct":1,"bm":0},{"ddd":0,"ind":10,"ty":4,"nm":"body","sr":1,"ks":{"o":{"a":0,"k":100,"ix":11},"r":{"a":0,"k":0,"ix":10},"p":{"a":1,"k":[{"i":{"x":0.667,"y":1},"o":{"x":0.333,"y":0},"t":5,"s":[250,421.5,0],"to":[0,5,0],"ti":[0,5,0]},{"i":{"x":0.667,"y":1},"o":{"x":0.333,"y":0},"t":15,"s":[250,451.5,0],"to":[0,-5,0],"ti":[0,1.667,0]},{"i":{"x":0.667,"y":1},"o":{"x":0.333,"y":0},"t":26,"s":[250,391.5,0],"to":[0,-1.667,0],"ti":[0,-5,0]},{"i":{"x":0.667,"y":1},"o":{"x":0.333,"y":0},"t":37,"s":[250,441.5,0],"to":[0,5,0],"ti":[0,3.333,0]},{"t":48,"s":[250,421.5,0]}],"ix":2,"l":2},"a":{"a":0,"k":[0,55.511,0],"ix":1,"l":2},"s":{"a":0,"k":[100,100,100],"ix":6,"l":2}},"ao":0,"shapes":[{"ty":"gr","it":[{"ind":0,"ty":"sh","ix":1,"ks":{"a":0,"k":{"i":[[0,0],[0,-23.039],[0,0],[0,0],[0,0],[-19.672,9.005],[-43.044,0]],"o":[[19.652,9.013],[0,0],[0,0],[0,0],[0,-23.054],[0,0],[37.565,0]],"v":[[60.286,-46.365],[93.588,5.538],[93.588,55.511],[-93.588,55.511],[-93.588,5.538],[-60.249,-46.381],[1.174,-55.511]],"c":true},"ix":2},"nm":"Path 1","mn":"ADBE Vector Shape - Group","hd":false},{"ty":"st","c":{"a":0,"k":[0,0,0,1],"ix":3,"x":"var $bm_rt;\n$bm_rt = thisComp.layer('Main Stroke width - Color Ctrl').effect('Base Color')('Color');"},"o":{"a":0,"k":100,"ix":4},"w":{"a":0,"k":16,"ix":5,"x":"var $bm_rt;\n$bm_rt = thisComp.layer('Main Stroke width - Color Ctrl').effect('Stroke width')('Slider');"},"lc":2,"lj":2,"bm":0,"nm":"Stroke 1","mn":"ADBE Vector Graphic - Stroke","hd":false},{"ty":"tr","p":{"a":0,"k":[0,0],"ix":2},"a":{"a":0,"k":[0,0],"ix":1},"s":{"a":0,"k":[100,100],"ix":3},"r":{"a":0,"k":0,"ix":6},"o":{"a":0,"k":100,"ix":7},"sk":{"a":0,"k":0,"ix":4},"sa":{"a":0,"k":0,"ix":5},"nm":"Transform"}],"nm":"Group 1","np":2,"cix":2,"bm":0,"ix":1,"mn":"ADBE Vector Group","hd":false}],"ip":0,"op":60,"st":0,"ct":1,"bm":0},{"ddd":0,"ind":11,"ty":4,"nm":"mask","parent":10,"td":1,"sr":1,"ks":{"o":{"a":0,"k":100,"ix":11},"r":{"a":0,"k":0,"ix":10},"p":{"a":0,"k":[0,2.472,0],"ix":2,"l":2},"a":{"a":0,"k":[0,0,0],"ix":1,"l":2},"s":{"a":0,"k":[100,100,100],"ix":6,"l":2}},"ao":0,"shapes":[{"ty":"gr","it":[{"ind":0,"ty":"sh","ix":1,"ks":{"a":0,"k":{"i":[[0,0],[0,0],[0,0],[-31.647,0],[0,0],[0,-31.647]],"o":[[0,0],[0,0],[0,-31.647],[0,0],[31.647,0],[0,0]],"v":[[93.992,53.739],[-93.992,53.739],[-93.992,3.562],[-36.691,-53.739],[36.691,-53.739],[93.992,3.562]],"c":true},"ix":2},"nm":"Path 1","mn":"ADBE Vector Shape - Group","hd":false},{"ty":"fl","c":{"a":0,"k":[0.96862745285,0.690196096897,0.450980395079,1],"ix":4},"o":{"a":0,"k":100,"ix":5},"r":1,"bm":0,"nm":"Fill 1","mn":"ADBE Vector Graphic - Fill","hd":false},{"ty":"tr","p":{"a":0,"k":[0,0],"ix":2},"a":{"a":0,"k":[0,0],"ix":1},"s":{"a":0,"k":[100,100],"ix":3},"r":{"a":0,"k":0,"ix":6},"o":{"a":0,"k":100,"ix":7},"sk":{"a":0,"k":0,"ix":4},"sa":{"a":0,"k":0,"ix":5},"nm":"Transform"}],"nm":"Group 1","np":2,"cix":2,"bm":0,"ix":1,"mn":"ADBE Vector Group","hd":false}],"ip":0,"op":60,"st":0,"ct":1,"bm":0},{"ddd":0,"ind":12,"ty":4,"nm":"shadow","parent":2,"tt":1,"tp":11,"sr":1,"ks":{"o":{"a":0,"k":100,"ix":11},"r":{"a":0,"k":0,"ix":10},"p":{"a":0,"k":[250.422,296.775,0],"ix":2,"l":2},"a":{"a":0,"k":[0,0,0],"ix":1,"l":2},"s":{"a":0,"k":[100,100,100],"ix":6,"l":2}},"ao":0,"shapes":[{"ty":"gr","it":[{"ind":0,"ty":"sh","ix":1,"ks":{"a":0,"k":{"i":[[17.623,0],[0,0],[-19.974,-65.412],[-25.036,0],[0,0],[-10.348,21.046]],"o":[[0,0],[-17.623,0],[10.348,21.046],[0,0],[25.036,0],[22.322,-57.586]],"v":[[36.269,-73.949],[-37.113,-73.949],[-81.012,38.419],[-23.975,73.949],[23.132,73.949],[80.169,38.419]],"c":true},"ix":2},"nm":"Path 1","mn":"ADBE Vector Shape - Group","hd":false},{"ty":"fl","c":{"a":0,"k":[0.831372559071,0.419607847929,0.360784322023,1],"ix":4},"o":{"a":0,"k":100,"ix":5},"r":1,"bm":0,"nm":"Fill 1","mn":"ADBE Vector Graphic - Fill","hd":false},{"ty":"tr","p":{"a":0,"k":[0,0],"ix":2},"a":{"a":0,"k":[0,0],"ix":1},"s":{"a":0,"k":[100,100],"ix":3},"r":{"a":0,"k":0,"ix":6},"o":{"a":0,"k":100,"ix":7},"sk":{"a":0,"k":0,"ix":4},"sa":{"a":0,"k":0,"ix":5},"nm":"Transform"}],"nm":"Group 1","np":2,"cix":2,"bm":0,"ix":1,"mn":"ADBE Vector Group","hd":false}],"ip":0,"op":60,"st":0,"ct":1,"bm":0},{"ddd":0,"ind":13,"ty":4,"nm":"body","parent":10,"sr":1,"ks":{"o":{"a":0,"k":100,"ix":11},"r":{"a":0,"k":0,"ix":10},"p":{"a":0,"k":[0,2.472,0],"ix":2,"l":2},"a":{"a":0,"k":[0,0,0],"ix":1,"l":2},"s":{"a":0,"k":[100,100,100],"ix":6,"l":2}},"ao":0,"shapes":[{"ty":"gr","it":[{"ind":0,"ty":"sh","ix":1,"ks":{"a":0,"k":{"i":[[0,0],[0,0],[0,0],[-31.647,0],[0,0],[0,-31.647]],"o":[[0,0],[0,0],[0,-31.647],[0,0],[31.647,0],[0,0]],"v":[[93.992,53.739],[-93.992,53.739],[-93.992,3.562],[-36.691,-53.739],[36.691,-53.739],[93.992,3.562]],"c":true},"ix":2},"nm":"Path 1","mn":"ADBE Vector Shape - Group","hd":false},{"ty":"fl","c":{"a":0,"k":[0.96862745285,0.690196096897,0.450980395079,1],"ix":4},"o":{"a":0,"k":100,"ix":5},"r":1,"bm":0,"nm":"Fill 1","mn":"ADBE Vector Graphic - Fill","hd":false},{"ty":"tr","p":{"a":0,"k":[0,0],"ix":2},"a":{"a":0,"k":[0,0],"ix":1},"s":{"a":0,"k":[100,100],"ix":3},"r":{"a":0,"k":0,"ix":6},"o":{"a":0,"k":100,"ix":7},"sk":{"a":0,"k":0,"ix":4},"sa":{"a":0,"k":0,"ix":5},"nm":"Transform"}],"nm":"Group 1","np":2,"cix":2,"bm":0,"ix":1,"mn":"ADBE Vector Group","hd":false}],"ip":0,"op":60,"st":0,"ct":1,"bm":0}],"markers":[]}